PyCmpltrtok/common.py
PyCmpltrtok/common_3d.py
PyCmpltrtok/common_accelerate.py
PyCmpltrtok/common_audio.py
PyCmpltrtok/common_data_struc.py
PyCmpltrtok/common_file_ops.py
PyCmpltrtok/common_gpgpu.py
PyCmpltrtok/common_hf.py
PyCmpltrtok/common_logging.py
PyCmpltrtok/common_np.py
PyCmpltrtok/common_opencv.py
PyCmpltrtok/common_pymongo.py
PyCmpltrtok/common_redis.py
PyCmpltrtok/common_streamlit.py
PyCmpltrtok/common_torch.py
PyCmpltrtok/common_visualize.py
PyCmpltrtok/util_mongo.py
PyCmpltrtok/auth/mongo/__init__.py
PyCmpltrtok/auth/mongo/conn.py
PyCmpltrtok/auth/mongo/dump_tpl.py
PyCmpltrtok/auth/redis/__init__.py
PyCmpltrtok/auth/redis/conn.py
PyCmpltrtok/auth/redis/dump_tpl.py
PyCmpltrtok/data/cifar10/load_cifar10.py
PyCmpltrtok/data/cifar10/routines.py
PyCmpltrtok/data/mnist/load_mnist.py
PyCmpltrtok/data/mnist/routines.py
PyCmpltrtok/util/check_env.py
PyCmpltrtok/util/check_python.py
PyCmpltrtok/util/check_scores.py
PyCmpltrtok/util/check_students.py
PyCmpltrtok/util/choose_student.py
PyCmpltrtok/util/demo_long_live.py
PyCmpltrtok/util/mat_table.py
PyCmpltrtok/util/test_port_by_fastapi.py
PyCmpltrtok/util/test_tf_gpu.py
PyCmpltrtok/util/translate_ns.py
PyCmpltrtok/util/translate_s.py
PyCmpltrtok-0.0.1.dist-info/COPYING
PyCmpltrtok-0.0.1.dist-info/LICENSE
PyCmpltrtok-0.0.1.dist-info/METADATA
PyCmpltrtok-0.0.1.dist-info/WHEEL
PyCmpltrtok-0.0.1.dist-info/top_level.txt
PyCmpltrtok-0.0.1.dist-info/RECORD
