Metadata-Version: 2.2
Name: PyCmpltrtok
Version: 0.0.1
Summary: A collection of the common python3 codes used in Cmpltrtok's projects
Author-email: Yun-Peng Pei <belarc@163.com>
License:                                  Apache License
Project-URL: Homepage, https://github.com/cmpltrtok20/PyCmpltrtok
Project-URL: Issues, https://github.com/cmpltrtok20/PyCmpltrtok/issues
Classifier: Programming Language :: Python :: 3
Classifier: Operating System :: POSIX :: Linux
Requires-Python: >=3.8
License-File: LICENSE
License-File: COPYING
